Yikai_helper_funcs/__init__.py
Yikai_helper_funcs/_nbdev.py
Yikai_helper_funcs/bayes_opt.py
Yikai_helper_funcs/core.py
Yikai_helper_funcs/imports.py
Yikai_helper_funcs/model_iterator.py
Yikai_helper_funcs/params.py
Yikai_helper_funcs/tab_ae.py
Yikai_helper_funcs-0.1.6.dist-info/LICENSE
Yikai_helper_funcs-0.1.6.dist-info/METADATA
Yikai_helper_funcs-0.1.6.dist-info/WHEEL
Yikai_helper_funcs-0.1.6.dist-info/entry_points.txt
Yikai_helper_funcs-0.1.6.dist-info/top_level.txt
Yikai_helper_funcs-0.1.6.dist-info/RECORD
