Metadata-Version: 2.1
Name: Yikai-helper-funcs
Version: 0.1.6
Summary: Test nbdev for developing packages for self-resue
Home-page: https://github.com/DavidykZhao/Yikai_helper_funcs/tree/master/
Author: Yikai Zhao
Author-email: zdwzhaoyikai@gmail.com
License: Apache Software License 2.0
Keywords: test
Platform: UNKNOWN
Classifier: Development Status :: 3 - Alpha
Classifier: Intended Audience :: Developers
Classifier: License :: OSI Approved :: Apache Software License
Classifier: Natural Language :: English
Classifier: Programming Language :: Python :: 3.6
Classifier: Programming Language :: Python :: 3.7
Classifier: Programming Language :: Python :: 3.8
Requires-Python: >=3.6
Requires-Dist: lightgbm (>=3.0.0)
Requires-Dist: xgboost
Requires-Dist: fastai
Requires-Dist: fastcore
Requires-Dist: sklearn
Requires-Dist: bayesian-optimization
Requires-Dist: pathlib
